{
  "area_coaches": {
    "Darian Spikes": {
      "name": "Darian Spikes",
      "email": "dspikes@ayvazpizza.com",
      "area": "Area 2011"
    },
    "Ebony Simmons": {
      "name": "Ebony Simmons",
      "email": "esimmons@ayvazpizza.com",
      "area": "Area 2016"
    },
    "Jadon McNeil": {
      "name": "Jadon McNeil",
      "email": "jmcneil@ayvazpizza.com",
      "area": "Area 2022"
    },
    "Jorge Garcia": {
      "name": "Jorge Garcia",
      "email": "jgarcia@ayvazpizza.com",
      "area": "Area 2000"
    },
    "Marc Gannon": {
      "name": "Marc Gannon",
      "email": "mgannon@ayvazpizza.com",
      "area": "Area 2015"
    },
    "Michelle Meehan": {
      "name": "Michelle Meehan",
      "email": "mmeehan@ayvazpizza.com",
      "area": "Area 2034"
    },
    "Alpha Garza": {
      "name": "Alpha Garza",
      "email": "agarza@ayvazpizza.com",
      "area": "Area 2042"
    },
    "Amanda Spikes": {
      "name": "Amanda Spikes",
      "email": " aspikes@ayvazpizza.com",
      "area": "Area 2001"
    },
    "Imran Awan (Kiosks-Express)": {
      "name": "Imran Awan (Kiosks-Express)",
      "email": "imranaway@gulshaninc.com",
      "area": "Area 2100"
    },
    "Larry (Steve) Battenfield": {
      "name": "Larry (Steve) Battenfield",
      "email": "sbattenfield@ayvazpizza.com",
      "area": "Area 2050"
    },
    "Thomas Cobb": {
      "name": "Thomas Cobb",
      "email": "tcobb@ayvazpizza.com",
      "area": "Area 2030"
    },
    "Jacob Maldonado": {
      "name": "Jacob Maldonado",
      "email": "jmaldonado@ayvazpizza.com",
      "area": "Area 2021"
    },
    "Joel Salinas": {
      "name": "Joel Salinas",
      "email": "jsalinas@ayvazpizza.com",
      "area": "Area 2019"
    },
    "Jose Flores": {
      "name": "Jose Flores",
      "email": " jflores@ayvazpizza.com",
      "area": "Area 2027"
    },
    "Lee Duran": {
      "name": "Lee Duran",
      "email": "lduran@ayvazpizza.com",
      "area": "Area 2035"
    },
    "Maria Avila": {
      "name": "Maria Avila",
      "email": "mavila@ayvazpizza.com",
      "area": "Area 2038"
    },
    "Michelle Cavazos": {
      "name": "Michelle Cavazos",
      "email": "mcavazos@ayvazpizza.com",
      "area": "Area 2040"
    },
    "Roberto Sanchez": {
      "name": "Roberto Sanchez",
      "email": "rsanchez@ayvazpizza.com",
      "area": "Area 2029"
    },
    "Ruben Gonzalez": {
      "name": "Ruben Gonzalez",
      "email": "rgonzalez@ayvazpizza.com",
      "area": "Area 2047"
    },
    "Debbra Selvig": {
      "name": "Debbra Selvig",
      "email": "dselvig@ayvazpizza.com",
      "area": "Area 2013"
    },
    "Derek King": {
      "name": "Derek King",
      "email": "dking@ayvazpizza.com",
      "area": "Area 2057"
    },
    "Scott Fiksdal": {
      "name": "Scott Fiksdal",
      "email": "sfiksdal@ayvazpizza.com",
      "area": "Area 2049"
    },
    "Szymon Lubas": {
      "name": "Szymon Lubas",
      "email": "slubas@ayvazpizza.com",
      "area": "Area 2044"
    },
    "Va Vang": {
      "name": "Va Vang",
      "email": "vvang@ayvazpizza.com",
      "area": "Area 2012"
    },
    "Jeffrey Washburn": {
      "name": "Jeffrey Washburn",
      "email": "jwashburn@ayvazpizza.com",
      "area": "Area 2054"
    },
    "Maria Delgado-Perez": {
      "name": "Maria Delgado-Perez",
      "email": "mperez@ayvazpizza.com",
      "area": "Area 2006"
    },
    "Rachel Hightower": {
      "name": "Rachel Hightower",
      "email": "rhightower@ayvazpizza.com",
      "area": "Area 2045"
    },
    "Ravin Lott": {
      "name": "Ravin Lott",
      "email": "rlott@ayvazpizza.com",
      "area": "Area 2051"
    },
    "Reginald Brown": {
      "name": "Reginald Brown",
      "email": "rbrown@ayvazpizza.com",
      "area": "Area 2046"
    },
    "Robert Thomas": {
      "name": "Robert Thomas",
      "email": "rthomas@ayvazpizza.com",
      "area": "Area 2037"
    },
    "Shayda Willison": {
      "name": "Shayda Willison",
      "email": "swillison@ayvazpizza.com",
      "area": "Area 2059"
    },
    "Emmanuel Boateng": {
      "name": "Emmanuel Boateng",
      "email": "eboateng@ayvazpizza.com",
      "area": "Area 2017"
    },
    "Erin Pizzo": {
      "name": "Erin Pizzo",
      "email": "epizzo@ayvazpizza.com",
      "area": "Area 2004"
    },
    "Royal Mitchell": {
      "name": "Royal Mitchell",
      "email": "rmitchell@ayvazpizza.com",
      "area": "Area 2009"
    },
    "Russell Kowalczyk": {
      "name": "Russell Kowalczyk",
      "email": "rkowalczyk@ayvazpizza.com",
      "area": "Area 2048"
    },
    "Stepfen White": {
      "name": "Stepfen White",
      "email": "swhite@ayvazpizza.com",
      "area": "Area 2041"
    },
    "Brenda Marta": {
      "name": "Brenda Marta",
      "email": "bmarta@ayvazpizza.com",
      "area": "Area 2002"
    },
    "Constance Miranda": {
      "name": "Constance Miranda",
      "email": "cmiranda@ayvazpizza.com",
      "area": "Area 2010"
    },
    "Eric Harstine": {
      "name": "Eric Harstine",
      "email": "eharstine@ayvazpizza.com",
      "area": "Area 2033"
    },
    "Javier Martinez": {
      "name": "Javier Martinez",
      "email": "jmartinez@ayvazpizza.com",
      "area": "Area 2024"
    },
    "Kevin Dunn": {
      "name": "Kevin Dunn",
      "email": "kdunn@ayvazpizza.com",
      "area": "Area 2055"
    },
    "Max Losey": {
      "name": "Max Losey",
      "email": "mlosey@ayvazpizza.com",
      "area": "Area 2039"
    },
    "Oscar Gutierrez": {
      "name": "Oscar Gutierrez",
      "email": "ogutierrez@ayvazpizza.com",
      "area": "Area 2043"
    },
    "Tami Elliott-Baker": {
      "name": "Tami Elliott-Baker",
      "email": "tbaker@ayvazpizza.com",
      "area": "Area 2008"
    },
    "Bahram Kaman": {
      "name": "Bahram Kaman",
      "email": "bkaman@ayvazpizza.com",
      "area": "Area 2025"
    },
    "Brian Marzan": {
      "name": "Brian Marzan",
      "email": "bmarzan@ayvazpizza.com",
      "area": "Area 2032"
    },
    "Cesar Robles": {
      "name": "Cesar Robles",
      "email": "crobles@ayvazpizza.com",
      "area": "Area 2007"
    },
    "Donna Dittmar": {
      "name": "Donna Dittmar",
      "email": "ddittmar@ayvazpizza.com",
      "area": "Area 2014"
    },
    "Freddy (Antonio) Sandoval": {
      "name": "Freddy (Antonio) Sandoval",
      "email": "fsandoval@ayvazpizza.com",
      "area": "Area 2031"
    },
    "Jesse Luna": {
      "name": "Jesse Luna",
      "email": "jluna@ayvazpizza.com",
      "area": "Area 2028"
    },
    "Kyle Smith": {
      "name": "Kyle Smith",
      "email": "kylesmith@ayvazpizza.com",
      "area": "Area 2056"
    },
    "Luigi Andinolfi": {
      "name": "Luigi Andinolfi",
      "email": "landinolfi@ayvazpizza.com",
      "area": "Area 2036"
    }
  },
  "region_coaches": {
    "Harold Lacoste": {
      "name": "Harold Lacoste",
      "email": "hlacoste@ayvazpizza.com"
    },
    "Jerry Warren": {
      "name": "Jerry Warren",
      "email": "jwarren@ayvazpizza.com"
    },
    "Jose Lozano Sr.": {
      "name": "Jose Lozano Sr.",
      "email": "jlozano@ayvazpizza.com"
    },
    "Lori Schwartz": {
      "name": "Lori Schwartz",
      "email": "lschwartz@ayvazpizza.com"
    },
    "Papa Diack": {
      "name": "Papa Diack",
      "email": "pdiack@ayvazpizza.com"
    },
    "Preston Arnwine": {
      "name": "Preston Arnwine",
      "email": "parnwine@ayvazpizza.com"
    },
    "Terrance Spillane": {
      "name": "Terrance Spillane",
      "email": "tspillane@ayvazpizza.com"
    },
    "Theresa McDaniel": {
      "name": "Theresa McDaniel",
      "email": "tmcdaniel@ayvazpizza.com"
    }
  },
  "vp": {
    "Matt Hester": {
      "name": "Matt Hester",
      "email": "mhester@ayvazpizza.com"
    },
    "Tracy Krumwiede": {
      "name": "Tracy Krumwiede",
      "email": "tkrumwiede@ayvazpizza.com"
    },
    "Chad Magner": {
      "name": "Chad Magner",
      "email": "cmagner@ayvazpizza.com"
    }
  }
}